{"view": {"allAccessPoints": [], "apiFoundryUrl": "https://dev.socrata.com/foundry/data.cityofnewyork.us/xp25-gxux", "attachments": [{"name": "LinkNYC New Site Permit Applications_Data Dictionary.xlsx", "href": "/api/views/xp25-gxux/files/af747b23-07c3-499c-adea-2b1a589f536e?download=true&filename=LinkNYC New Site Permit Applications_Data Dictionary.xlsx", "link": "<a target=\"_blank\" href=\"/api/views/xp25-gxux/files/af747b23-07c3-499c-adea-2b1a589f536e?download=true&ampfilename=LinkNYC New Site Permit Applications_Data Dictionary.xlsx\">LinkNYC New Site Permit Applications_Data Dictionary.xlsx</a>"}], "attribution": "Office of Technology and Innovation (OTI)", "attributionLink": null, "blobFilename": null, "blobId": null, "blobMimeType": null, "blobType": false, "bootstrapUrl": "/d/xp25-gxux/visualization", "canPublish": false, "cartoUrl": "http://oneclick.cartodb.com/?file=https://data.cityofnewyork.us/api/views/xp25-gxux/rows.geojson?accessType=DOWNLOAD", "category": "Social Services", "collectionParentView": null, "parentView": null, "columns": [{"id": 575834780, "name": "Site ID", "fieldName": "site_id", "position": 1, "description": "The unique ID for each LinkNYC kiosk site in the format: Borough-Community Board-Payphone ID (e.g., mn-03-123265) ", "width": 100, "dataTypeName": "text", "renderTypeName": "text", "tableColumnId": 68608596, "cachedContents": {"non_null": "330", "largest": "SI-01-GF55246", "null": "0", "top": [{"item": "BX-10-GF22747", "count": "1"}, {"item": "MN-12-120807", "count": "1"}, {"item": "MN-08-GF0910", "count": "1"}, {"item": "QU-12-GF44832", "count": "1"}, {"item": "QU-13-GF44801", "count": "1"}, {"item": "BK-16-150013", "count": "1"}, {"item": "MN-11-GF0922", "count": "1"}, {"item": "QU-10-GF44812", "count": "1"}, {"item": "QU-12-124672", "count": "1"}, {"item": "BK-16-132774", "count": "1"}, {"item": "MN-09-120409", "count": "1"}, {"item": "MN-08-GF0909", "count": "1"}, {"item": "SI-01-159857", "count": "1"}, {"item": "QU-01-GF44791", "count": "1"}, {"item": "BK-01-GF34906", "count": "1"}, {"item": "BK-11-GF34845", "count": "1"}, {"item": "BX-02-GF22617", "count": "1"}, {"item": "QU-13-GF44807", "count": "1"}, {"item": "BK-03-144136", "count": "1"}, {"item": "BK-16-158252", "count": "1"}], "smallest": "BK-01-125285", "count": "330", "cardinality": "330"}, "format": {"align": "left"}, "flags": null}, {"id": 575834781, "name": "Planned Kiosk Type", "fieldName": "planned_kiosk_type", "position": 2, "description": "Indicates style of kiosk (LINK1.0, LINK5G, and LINK5G_NoAd) or public pay phone.", "dataTypeName": "text", "renderTypeName": "text", "tableColumnId": 146728824, "cachedContents": {"non_null": "330", "largest": "LINK5G_NonAd", "null": "0", "top": [{"item": "LINK5G_Ad", "count": "205"}, {"item": "LINK5G_NonAd", "count": "90"}, {"item": "LINK1.0", "count": "35"}], "smallest": "LINK1.0", "count": "330", "cardinality": "3"}, "format": {}, "flags": null}, {"id": 575834818, "name": "Installation Status ", "fieldName": "installation_status_", "position": 3, "description": "Indicates the current status, including planning for utility connections, DOT permitting, and construction.", "dataTypeName": "text", "renderTypeName": "text", "tableColumnId": 146972014, "cachedContents": {"non_null": "330", "largest": "Ready for PreCx", "null": "0", "top": [{"item": "PreCx", "count": "124"}, {"item": "Live", "count": "73"}, {"item": "Planning", "count": "58"}, {"item": "Installed", "count": "51"}, {"item": "Ready for Installation", "count": "11"}, {"item": "Ready for Activation", "count": "7"}, {"item": "Ready for PreCx", "count": "4"}, {"item": "Ready for Cx", "count": "2"}], "smallest": "Installed", "count": "330", "cardinality": "8"}, "format": {}, "flags": null}, {"id": 575834782, "name": "PPT ID", "fieldName": "ppt_id", "position": 4, "description": "An 6-digit ID generated by the database - a unique number for each LINK and Pay Public Telephone (PPT)", "dataTypeName": "text", "renderTypeName": "text", "tableColumnId": 139558285, "cachedContents": {"non_null": "134", "largest": "GF33287", "null": "196", "top": [{"item": "100042", "count": "1"}, {"item": "100074", "count": "1"}, {"item": "103162", "count": "1"}, {"item": "106058", "count": "1"}, {"item": "107137", "count": "1"}, {"item": "107629", "count": "1"}, {"item": "107770", "count": "1"}, {"item": "108654", "count": "1"}, {"item": "108732", "count": "1"}, {"item": "108912", "count": "1"}, {"item": "109192", "count": "1"}, {"item": "109283", "count": "1"}, {"item": "114989", "count": "1"}, {"item": "115284", "count": "1"}, {"item": "118455", "count": "1"}, {"item": "118473", "count": "1"}, {"item": "118523", "count": "1"}, {"item": "118847", "count": "1"}, {"item": "119607", "count": "1"}, {"item": "119612", "count": "1"}], "smallest": "100042", "count": "330", "cardinality": "134"}, "format": {}, "flags": null}, {"id": 575834783, "name": "Legacy ID", "fieldName": "legacy_id", "position": 5, "description": "The ID number for the LinkNYC kiosk", "dataTypeName": "text", "renderTypeName": "text", "tableColumnId": 146316267, "cachedContents": {"non_null": "130", "largest": "SC90851", "null": "200", "top": [{"item": "10058", "count": "1"}, {"item": "10100", "count": "1"}, {"item": "10375", "count": "1"}, {"item": "10511", "count": "1"}, {"item": "12103", "count": "1"}, {"item": "12120", "count": "1"}, {"item": "12319", "count": "1"}, {"item": "12320", "count": "1"}, {"item": "12322", "count": "1"}, {"item": "1255", "count": "1"}, {"item": "13070", "count": "1"}, {"item": "1355", "count": "1"}, {"item": "14136", "count": "1"}, {"item": "14138", "count": "1"}, {"item": "14142", "count": "1"}, {"item": "14173", "count": "1"}, {"item": "1435", "count": "1"}, {"item": "15000", "count": "1"}, {"item": "15023", "count": "1"}, {"item": "15048", "count": "1"}], "smallest": "10058", "count": "330", "cardinality": "130"}, "format": {}, "flags": null}, {"id": 575834784, "name": "Borough", "fieldName": "borough", "position": 6, "description": "The New York City borough where the hotspots are located.\n", "width": 184, "dataTypeName": "text", "renderTypeName": "text", "tableColumnId": 35863871, "cachedContents": {"non_null": "330", "largest": "Staten Island", "null": "0", "top": [{"item": "Queens", "count": "135"}, {"item": "Brooklyn", "count": "81"}, {"item": "Manhattan", "count": "52"}, {"item": "Bronx", "count": "46"}, {"item": "Staten Island", "count": "16"}], "smallest": "Bronx", "count": "330", "cardinality": "5"}, "format": {"align": "left"}, "flags": null}, {"id": 575834785, "name": "Council District", "fieldName": "council_district", "position": 7, "description": "Council District is the lawmaking body of the City of New York.  There are 51 districts throughout NYC's five boroughs.", "width": 100, "dataTypeName": "number", "renderTypeName": "number", "tableColumnId": 54034269, "cachedContents": {"non_null": "330", "largest": "50", "null": "0", "top": [{"item": "27", "count": "38"}, {"item": "26", "count": "23"}, {"item": "28", "count": "17"}, {"item": "49", "count": "14"}, {"item": "1", "count": "14"}, {"item": "17", "count": "13"}, {"item": "10", "count": "13"}, {"item": "4", "count": "12"}, {"item": "34", "count": "12"}, {"item": "23", "count": "11"}, {"item": "33", "count": "11"}, {"item": "38", "count": "11"}, {"item": "42", "count": "11"}, {"item": "31", "count": "11"}, {"item": "24", "count": "10"}, {"item": "41", "count": "10"}, {"item": "15", "count": "9"}, {"item": "18", "count": "9"}, {"item": "37", "count": "8"}, {"item": "35", "count": "7"}], "smallest": "1", "count": "330", "cardinality": "41"}, "format": {"precisionStyle": "standard", "align": "left"}, "flags": null}, {"id": 575834786, "name": "Community Board", "fieldName": "cb", "position": 8, "description": "Community Board: An appointed advisory group from a variety of districts throughout NYC's five boroughs.  They deal with issues such as zoning, land usage, and any other matter related to the quality of life of their residents.\n", "width": 124, "dataTypeName": "number", "renderTypeName": "number", "tableColumnId": 35863873, "cachedContents": {"non_null": "330", "largest": "501", "null": "0", "top": [{"item": "412", "count": "66"}, {"item": "103", "count": "19"}, {"item": "402", "count": "17"}, {"item": "304", "count": "17"}, {"item": "501", "count": "16"}, {"item": "202", "count": "15"}, {"item": "316", "count": "15"}, {"item": "112", "count": "13"}, {"item": "205", "count": "12"}, {"item": "403", "count": "11"}, {"item": "413", "count": "11"}, {"item": "108", "count": "9"}, {"item": "306", "count": "8"}, {"item": "301", "count": "8"}, {"item": "207", "count": "8"}, {"item": "209", "count": "7"}, {"item": "414", "count": "7"}, {"item": "309", "count": "7"}, {"item": "407", "count": "7"}, {"item": "302", "count": "7"}], "smallest": "102", "count": "330", "cardinality": "39"}, "format": {"precisionStyle": "standard", "align": "right"}, "flags": null}, {"id": 575834788, "name": "Final Submission (A)", "fieldName": "final_submission_a_", "position": 9, "description": "Submission Date from vendor for review.", "dataTypeName": "calendar_date", "renderTypeName": "calendar_date", "tableColumnId": 146728823, "cachedContents": {"non_null": "326", "largest": "2023-04-06T00:00:00.000", "null": "4", "top": [{"item": "2022-08-09T00:00:00.000", "count": "103"}, {"item": "2021-10-08T00:00:00.000", "count": "52"}, {"item": "2021-11-30T00:00:00.000", "count": "28"}, {"item": "2022-09-23T00:00:00.000", "count": "28"}, {"item": "2022-03-08T00:00:00.000", "count": "21"}, {"item": "2022-11-17T00:00:00.000", "count": "19"}, {"item": "2022-01-28T00:00:00.000", "count": "16"}, {"item": "2021-08-31T00:00:00.000", "count": "12"}, {"item": "2022-04-01T00:00:00.000", "count": "12"}, {"item": "2022-05-13T00:00:00.000", "count": "10"}, {"item": "2022-10-28T00:00:00.000", "count": "7"}, {"item": "2021-12-21T00:00:00.000", "count": "5"}, {"item": "2022-11-03T00:00:00.000", "count": "2"}, {"item": "2021-04-06T00:00:00.000", "count": "2"}, {"item": "2021-08-06T00:00:00.000", "count": "2"}, {"item": "2021-05-14T00:00:00.000", "count": "2"}, {"item": "2022-02-23T00:00:00.000", "count": "1"}, {"item": "2022-08-17T00:00:00.000", "count": "1"}, {"item": "2023-02-10T00:00:00.000", "count": "1"}, {"item": "2022-09-16T00:00:00.000", "count": "1"}], "smallest": "2021-04-06T00:00:00.000", "count": "330", "cardinality": "21"}, "format": {}, "flags": null}, {"id": 575834789, "name": "GF Permit Application ID", "fieldName": "gf_permit_appl_id", "position": 10, "description": "The new site permit application number.\n", "width": 220, "dataTypeName": "number", "renderTypeName": "number", "tableColumnId": 35863882, "cachedContents": {"non_null": "225", "largest": "90459", "null": "105", "top": [{"item": "90196", "count": "2"}, {"item": "90198", "count": "2"}, {"item": "90199", "count": "2"}, {"item": "90452", "count": "1"}, {"item": "11765", "count": "1"}, {"item": "90110", "count": "1"}, {"item": "90245", "count": "1"}, {"item": "90434", "count": "1"}, {"item": "90200", "count": "1"}, {"item": "90433", "count": "1"}, {"item": "71381", "count": "1"}, {"item": "81286", "count": "1"}, {"item": "90170", "count": "1"}, {"item": "90459", "count": "1"}, {"item": "90225", "count": "1"}, {"item": "90307", "count": "1"}, {"item": "90354", "count": "1"}, {"item": "90157", "count": "1"}, {"item": "90176", "count": "1"}, {"item": "90202", "count": "1"}], "smallest": "11765", "count": "330", "cardinality": "222"}, "format": {"precisionStyle": "standard", "noCommas": "true", "align": "right"}, "flags": null}, {"id": 575834790, "name": "GF DoITT Submitted to CB (A)", "fieldName": "gf_doitt_submitted_to_cb_a", "position": 11, "description": "Information Submitted to Community Board on this date\n", "width": 100, "dataTypeName": "calendar_date", "renderTypeName": "calendar_date", "tableColumnId": 47417518, "cachedContents": {"non_null": "213", "largest": "2023-01-04T00:00:00.000", "null": "117", "top": [{"item": "2023-01-04T00:00:00.000", "count": "90"}, {"item": "2022-11-16T00:00:00.000", "count": "22"}, {"item": "2022-10-17T00:00:00.000", "count": "17"}, {"item": "2021-10-28T00:00:00.000", "count": "16"}, {"item": "2022-02-11T00:00:00.000", "count": "14"}, {"item": "2022-10-18T00:00:00.000", "count": "12"}, {"item": "2021-09-23T00:00:00.000", "count": "11"}, {"item": "2022-05-13T00:00:00.000", "count": "9"}, {"item": "2022-04-08T00:00:00.000", "count": "8"}, {"item": "2022-11-18T00:00:00.000", "count": "8"}, {"item": "2022-11-17T00:00:00.000", "count": "4"}, {"item": "2021-11-22T00:00:00.000", "count": "2"}], "smallest": "2021-09-23T00:00:00.000", "count": "330", "cardinality": "12"}, "format": {"view": "date", "align": "left"}, "flags": null}, {"id": 575834791, "name": "GF CB Comment Period Ends (A)", "fieldName": "gf_cb_comment_period_ends_a", "position": 12, "description": "Community Board Comment Period Ends on this date\n", "width": 100, "dataTypeName": "calendar_date", "renderTypeName": "calendar_date", "tableColumnId": 47417519, "cachedContents": {"non_null": "30", "largest": "2022-12-18T00:00:00.000", "null": "300", "top": [{"item": "2021-12-27T00:00:00.000", "count": "16"}, {"item": "2021-11-22T00:00:00.000", "count": "11"}, {"item": "2022-01-24T00:00:00.000", "count": "2"}, {"item": "2022-12-18T00:00:00.000", "count": "1"}], "smallest": "2021-11-22T00:00:00.000", "count": "330", "cardinality": "4"}, "format": {"view": "date", "align": "left"}, "flags": null}, {"id": 575834792, "name": "Street Address", "fieldName": "street_address", "position": 13, "description": "The name of the street that a site is located on.\n", "width": 232, "dataTypeName": "text", "renderTypeName": "text", "tableColumnId": 35863875, "cachedContents": {"non_null": "330", "largest": "CLASON POINT PARK", "null": "0", "top": [{"item": "75-20 ASTORIA BOULEVARD", "count": "2"}, {"item": "4228 MAIN STREET", "count": "1"}, {"item": "689 FT WASHINGTON AVENUE", "count": "1"}, {"item": "660 FLATBUSH AVENUE", "count": "1"}, {"item": "1354 MADISON AVENUE", "count": "1"}, {"item": "3177 WEBSTER AVENUE", "count": "1"}, {"item": "84 BEARD STREET", "count": "1"}, {"item": "18 BELMONT AVENUE", "count": "1"}, {"item": "184 CONOVER STREET", "count": "1"}, {"item": "1175 PARK AVENUE", "count": "1"}, {"item": "700 FAILE STREET", "count": "1"}, {"item": "40-39 CRESCENT STREET", "count": "1"}, {"item": "100 HORATIO STREET", "count": "1"}, {"item": "408 DE WITT AVENUE", "count": "1"}, {"item": "2861 WEBSTER AVENUE", "count": "1"}, {"item": "303 STANLEY AVENUE", "count": "1"}, {"item": "81-14 257TH STREET", "count": "1"}, {"item": "175 LYNHURST AVENUE", "count": "1"}, {"item": "1572 PITKIN AVENUE", "count": "1"}, {"item": "168-20 HILLSIDE AVENUE", "count": "1"}], "smallest": "100 HORATIO STREET", "count": "330", "cardinality": "329"}, "format": {"align": "left"}, "flags": null}, {"id": 575834793, "name": "Cross_Street 1", "fieldName": "cross_street_1", "position": 14, "description": "One of the closest streets to a potential LinkNYC site.\n", "width": 268, "dataTypeName": "text", "renderTypeName": "text", "tableColumnId": 35863876, "cachedContents": {"non_null": "330", "largest": "Zerega Ave", "null": "0", "top": [{"item": "BEDFORD AVENUE", "count": "4"}, {"item": "VICTORY BOULEVARD", "count": "4"}, {"item": "BROADWAY", "count": "4"}, {"item": "JUNIUS STREET", "count": "4"}, {"item": "41st Ave", "count": "4"}, {"item": "5th St", "count": "3"}, {"item": "HILLSIDE AVENUE", "count": "3"}, {"item": "Sutphin Boulevard", "count": "3"}, {"item": "WEST STREET", "count": "2"}, {"item": "EAST 93RD STREET", "count": "2"}, {"item": "Northern Boulevard", "count": "2"}, {"item": "262nd ST", "count": "2"}, {"item": "GRAND STREET", "count": "2"}, {"item": "BEARD STREET", "count": "2"}, {"item": "MYRTLE AVENUE", "count": "2"}, {"item": "Merrick Boulevard", "count": "2"}, {"item": "Louisiana Ave", "count": "2"}, {"item": "GATES AVENUE", "count": "2"}, {"item": "122ND STREET", "count": "2"}, {"item": "SOUTHERN BOULEVARD", "count": "2"}], "smallest": "107TH AVENUE", "count": "330", "cardinality": "285"}, "format": {"align": "left"}, "flags": null}, {"id": 575834794, "name": "Cross_Street 2", "fieldName": "cross_street_2", "position": 15, "description": "One of the closest streets to a potential LinkNYC site.\n", "width": 268, "dataTypeName": "text", "renderTypeName": "text", "tableColumnId": 35863877, "cachedContents": {"non_null": "330", "largest": "Zoller Road", "null": "0", "top": [{"item": "261st ST", "count": "3"}, {"item": "POWELL STREET", "count": "3"}, {"item": "Dead End", "count": "3"}, {"item": "DEAD END", "count": "3"}, {"item": "EAST 92ND STREET", "count": "2"}, {"item": "MONTGOMERY STREET", "count": "2"}, {"item": "CANAL STREET", "count": "2"}, {"item": "52nd Street", "count": "2"}, {"item": "ANTHONY AVENUE", "count": "2"}, {"item": "LORING PLACE SOUTH", "count": "2"}, {"item": "HARRISON AVENUE", "count": "2"}, {"item": "BARRY STREET", "count": "2"}, {"item": "264th ST", "count": "2"}, {"item": "MYRTLE AVENUE", "count": "2"}, {"item": "PURDY AVENUE", "count": "2"}, {"item": "Queens Plaza N", "count": "2"}, {"item": "VAN DYKE STREET", "count": "2"}, {"item": "W 167 STREET", "count": "2"}, {"item": "Dunkirk Drive", "count": "2"}, {"item": "STANTON STREET", "count": "2"}], "smallest": "109th Avenue", "count": "330", "cardinality": "301"}, "format": {"align": "left"}, "flags": null}, {"id": 575834795, "name": "IxN Corner", "fieldName": "ixn_code", "position": 16, "description": "The direction the Kiosk is facing.", "dataTypeName": "text", "renderTypeName": "text", "tableColumnId": 146728822, "cachedContents": {"non_null": "329", "largest": "West", "null": "1", "top": [{"item": "S", "count": "74"}, {"item": "E", "count": "70"}, {"item": "N", "count": "66"}, {"item": "W", "count": "62"}, {"item": "West", "count": "16"}, {"item": "North", "count": "14"}, {"item": "East", "count": "11"}, {"item": "South", "count": "8"}, {"item": "NW", "count": "4"}, {"item": "SE", "count": "2"}, {"item": "NE", "count": "1"}, {"item": "SW", "count": "1"}], "smallest": "E", "count": "330", "cardinality": "12"}, "format": {}, "flags": null}, {"id": 575834796, "name": "Postcode", "fieldName": "postcode", "position": 17, "description": "Five (5) digit postal code assigned by the United States Postal Service. ", "width": 100, "dataTypeName": "number", "renderTypeName": "number", "tableColumnId": 54034288, "cachedContents": {"non_null": "330", "largest": "11694", "null": "0", "top": [{"item": "11101", "count": "19"}, {"item": "11412", "count": "14"}, {"item": "11434", "count": "13"}, {"item": "10002", "count": "12"}, {"item": "11212", "count": "11"}, {"item": "11237", "count": "11"}, {"item": "11433", "count": "11"}, {"item": "11435", "count": "9"}, {"item": "11432", "count": "8"}, {"item": "11423", "count": "8"}, {"item": "11231", "count": "8"}, {"item": "11004", "count": "7"}, {"item": "10462", "count": "7"}, {"item": "10474", "count": "7"}, {"item": "11354", "count": "6"}, {"item": "11207", "count": "6"}, {"item": "10301", "count": "6"}, {"item": "10467", "count": "5"}, {"item": "10459", "count": "5"}, {"item": "10014", "count": "5"}], "smallest": "10002", "count": "330", "cardinality": "90"}, "format": {"precisionStyle": "standard", "noCommas": "true", "align": "right"}, "flags": null}, {"id": 575834797, "name": "Zoning", "fieldName": "zoningnumb", "position": 18, "description": "The type of zoning a kiosk is located in, displayed by its first letter followed by its zone.\n", "width": 220, "dataTypeName": "text", "renderTypeName": "text", "tableColumnId": 35863872, "cachedContents": {"non_null": "329", "largest": "R8 / C2-4", "null": "1", "top": [{"item": "C2-4", "count": "42"}, {"item": "C1-3", "count": "31"}, {"item": "M1-1", "count": "26"}, {"item": "C2-3", "count": "18"}, {"item": "C1-4", "count": "14"}, {"item": "C2-2", "count": "11"}, {"item": "M3-1", "count": "10"}, {"item": "M2-1", "count": "10"}, {"item": "C1-2", "count": "10"}, {"item": "M1-2", "count": "8"}, {"item": "C4-3", "count": "8"}, {"item": "C4-2", "count": "7"}, {"item": "C1-5", "count": "7"}, {"item": "R6", "count": "7"}, {"item": "R7-2", "count": "7"}, {"item": "M1-4", "count": "6"}, {"item": "R10", "count": "6"}, {"item": "C4-4", "count": "5"}, {"item": "C4-4A", "count": "5"}, {"item": "C8-2", "count": "5"}], "smallest": "C1-1", "count": "330", "cardinality": "67"}, "format": {"align": "left"}, "flags": null}, {"id": 575834798, "name": "Longitude", "fieldName": "longitude", "position": 19, "description": "Points that fall East or West of the Prime Meridian, expressed in degrees.\n", "width": 208, "dataTypeName": "number", "renderTypeName": "number", "tableColumnId": 35863870, "cachedContents": {"non_null": "330", "largest": "-73.7053516", "null": "0", "top": [{"item": "-74.141731", "count": "1"}, {"item": "-74.1406262", "count": "1"}, {"item": "-74.1373888", "count": "1"}, {"item": "-74.1346574", "count": "1"}, {"item": "-74.1301262", "count": "1"}, {"item": "-74.1277241", "count": "1"}, {"item": "-74.1192244", "count": "1"}, {"item": "-74.1033513", "count": "1"}, {"item": "-74.0804804", "count": "1"}, {"item": "-74.0779427", "count": "1"}, {"item": "-74.0776909", "count": "1"}, {"item": "-74.0771009", "count": "1"}, {"item": "-74.075901", "count": "1"}, {"item": "-74.0753967", "count": "1"}, {"item": "-74.0740457", "count": "1"}, {"item": "-74.0708488", "count": "1"}, {"item": "-74.0379322", "count": "1"}, {"item": "-74.025701", "count": "1"}, {"item": "-74.0170529", "count": "1"}, {"item": "-74.0168289", "count": "1"}], "smallest": "-74.141731", "count": "330", "cardinality": "330"}, "format": {"precisionStyle": "standard", "precision": "5", "align": "right"}, "flags": null}, {"id": 575834799, "name": "Latitude", "fieldName": "latitude", "position": 20, "description": "Points that fall North or South of the Equator, expressed in degrees.\n", "width": 196, "dataTypeName": "number", "renderTypeName": "number", "tableColumnId": 35863869, "cachedContents": {"non_null": "330", "largest": "40.8820398", "null": "0", "top": [{"item": "40.7489749", "count": "1"}, {"item": "40.6992378", "count": "1"}, {"item": "40.658116", "count": "1"}, {"item": "40.6717001", "count": "1"}, {"item": "40.762123", "count": "1"}, {"item": "40.8820398", "count": "1"}, {"item": "40.7484385", "count": "1"}, {"item": "40.8669715", "count": "1"}, {"item": "40.8387572", "count": "1"}, {"item": "40.771118", "count": "1"}, {"item": "40.745149", "count": "1"}, {"item": "40.7521201", "count": "1"}, {"item": "40.6797471", "count": "1"}, {"item": "40.7445751", "count": "1"}, {"item": "40.6781059", "count": "1"}, {"item": "40.6640729", "count": "1"}, {"item": "40.7538272", "count": "1"}, {"item": "40.634333", "count": "1"}, {"item": "40.736811", "count": "1"}, {"item": "40.7638316", "count": "1"}], "smallest": "40.5700406", "count": "330", "cardinality": "330"}, "format": {"precisionStyle": "standard", "precision": "5", "align": "right"}, "flags": null}, {"id": 575834800, "name": "Site in Business Improvement District (BID)?", "fieldName": "greenfield_in_bid_location", "position": 21, "description": "Is the LinkNYC Kiosk located in a Business Improvement District (BID)?\n", "width": 100, "dataTypeName": "text", "renderTypeName": "text", "tableColumnId": 45571080, "cachedContents": {"non_null": "322", "largest": "Yes", "null": "8", "top": [{"item": "No", "count": "296"}, {"item": "Yes", "count": "26"}], "smallest": "No", "count": "330", "cardinality": "2"}, "format": {"align": "left"}, "flags": null}, {"id": 575834801, "name": "BID", "fieldName": "bid", "position": 22, "description": "Is the LinkNYC Kiosk located in a Business Improvement District (BID)?\n", "width": 208, "dataTypeName": "text", "renderTypeName": "text", "tableColumnId": 35863880, "cachedContents": {"non_null": "29", "largest": "Village Alliance BID", "null": "301", "top": [{"item": "Chinatown", "count": "5"}, {"item": "Greater JFK", "count": "3"}, {"item": "Long Island City", "count": "2"}, {"item": "Jerome-Gun Hill", "count": "2"}, {"item": "Court-Livingston-Schermerhorn", "count": "2"}, {"item": "Lower East Side BID", "count": "2"}, {"item": "Myrtle Avenue Brooklyn Partnership?", "count": "2"}, {"item": "Pitkin Avenue", "count": "1"}, {"item": "Pitkin Avenue BID", "count": "1"}, {"item": "Southern Boulevard", "count": "1"}, {"item": "Sutphin Boulevard", "count": "1"}, {"item": "Village Alliance BID", "count": "1"}, {"item": "Church Avenue BID", "count": "1"}, {"item": "East Brooklyn BID", "count": "1"}, {"item": "Flatbush-Nostrand Junction?BID", "count": "1"}, {"item": "Madison Avenue", "count": "1"}, {"item": "Meatpacking", "count": "1"}, {"item": "Montague Street", "count": "1"}], "smallest": "Chinatown", "count": "330", "cardinality": "18"}, "format": {"align": "left"}, "flags": null}, {"id": 575834802, "name": "Link In Historic District", "fieldName": "historic_district", "position": 23, "description": "Is the LinkNYC Kiosk located in a historic district?\n", "width": 220, "dataTypeName": "text", "renderTypeName": "text", "tableColumnId": 35863878, "cachedContents": {"non_null": "330", "largest": "1", "null": "0", "top": [{"item": "0", "count": "326"}, {"item": "1", "count": "4"}], "smallest": "0", "count": "330", "cardinality": "2"}, "format": {"align": "left"}, "flags": null}, {"id": 575834803, "name": "Historic District Name", "fieldName": "historic_district_name", "position": 24, "description": "Name of historic district determined by the Landmarks Preservation Commission (LPC).", "dataTypeName": "text", "renderTypeName": "text", "tableColumnId": 146728821, "cachedContents": {"non_null": "9", "largest": "Upper East Side Historic District", "null": "321", "top": [{"item": "Expanded Carnegie Hill Historic District", "count": "2"}, {"item": "Park Avenue Historic District", "count": "2"}, {"item": "Upper East Side Historic District", "count": "2"}, {"item": "Gansevoort Market Historic District", "count": "1"}, {"item": "Greenwich Village Historic District", "count": "1"}, {"item": "SoHo-Cast Iron Historic District", "count": "1"}], "smallest": "Expanded Carnegie Hill Historic District", "count": "330", "cardinality": "6"}, "format": {}, "flags": null}, {"id": 575834804, "name": "Neighborhood Tabulation Area (NTA)", "fieldName": "neighborhood_tabulation_area_nta", "position": 25, "description": "Neighborhood identifiers to differentiate NYC's five boroughs\n", "width": 252, "dataTypeName": "text", "renderTypeName": "text", "tableColumnId": 54034554, "cachedContents": {"non_null": "323", "largest": "West Village", "null": "7", "top": [{"item": "Jamaica", "count": "22"}, {"item": "Hunters Point-Sunnyside-West Maspeth", "count": "17"}, {"item": "St. Albans", "count": "14"}, {"item": "Brownsville", "count": "13"}, {"item": "Hunts Point", "count": "11"}, {"item": "Jackson Heights", "count": "11"}, {"item": "Bushwick North", "count": "10"}, {"item": "Chinatown", "count": "9"}, {"item": "Upper East Side-Carnegie Hill", "count": "8"}, {"item": "Glen Oaks-Floral Park-New Hyde Park", "count": "8"}, {"item": "Carroll Gardens-Columbia Street-Red Hook", "count": "8"}, {"item": "Bushwick South", "count": "7"}, {"item": "Springfield Gardens North", "count": "7"}, {"item": "Hollis", "count": "6"}, {"item": "South Jamaica", "count": "6"}, {"item": "Queensbridge-Ravenswood-Long Island City", "count": "6"}, {"item": "Parkchester", "count": "6"}, {"item": "Washington Heights North", "count": "5"}, {"item": "Stapleton-Rosebank", "count": "5"}, {"item": "North Side-South Side", "count": "5"}], "smallest": "Baisley Park", "count": "330", "cardinality": "79"}, "format": {"align": "left"}, "flags": null}, {"id": 575834805, "name": "Building Identification Number (BIN)", "fieldName": "bin", "position": 26, "description": "Every real estate property has an assigned 7-digit number issued by the Department of City Planning.\n", "width": 100, "dataTypeName": "text", "renderTypeName": "text", "tableColumnId": 144101687, "cachedContents": {"non_null": "268", "largest": "5106796", "null": "62", "top": [{"item": "4541713", "count": "2"}, {"item": "2096680", "count": "2"}, {"item": "1000000", "count": "2"}, {"item": "1003219", "count": "1"}, {"item": "1003542", "count": "1"}, {"item": "1003627", "count": "1"}, {"item": "1003761", "count": "1"}, {"item": "1003957", "count": "1"}, {"item": "1004034", "count": "1"}, {"item": "1005433", "count": "1"}, {"item": "1005761", "count": "1"}, {"item": "1006068", "count": "1"}, {"item": "1007645", "count": "1"}, {"item": "1011368", "count": "1"}, {"item": "1012047", "count": "1"}, {"item": "1012154", "count": "1"}, {"item": "1034522", "count": "1"}, {"item": "1040861", "count": "1"}, {"item": "1040900", "count": "1"}, {"item": "1046915", "count": "1"}], "smallest": "1000000", "count": "330", "cardinality": "265"}, "format": {"precisionStyle": "standard", "noCommas": "true", "align": "right"}, "flags": null}, {"id": 575834807, "name": "Borough-Block-Lot( BBL)", "fieldName": "bbl", "position": 27, "description": "Every real estate property is identified by a set of 3 numbers for taxes, zoning, construction, and other purposes.\n", "width": 100, "dataTypeName": "text", "renderTypeName": "text", "tableColumnId": 144101688, "cachedContents": {"non_null": "319", "largest": "5028530001", "null": "11", "top": [{"item": "4010270050", "count": "3"}, {"item": "4000210020", "count": "2"}, {"item": "4122610001", "count": "2"}, {"item": "4000210040", "count": "2"}, {"item": "4087170001", "count": "2"}, {"item": "2039377501", "count": "2"}, {"item": "4043500050", "count": "2"}, {"item": "2039430001", "count": "2"}, {"item": "1003020001", "count": "1"}, {"item": "1003100020", "count": "1"}, {"item": "1003467501", "count": "1"}, {"item": "1003507502", "count": "1"}, {"item": "1003540012", "count": "1"}, {"item": "1003990008", "count": "1"}, {"item": "1004130008", "count": "1"}, {"item": "1004390028", "count": "1"}, {"item": "1004420007", "count": "1"}, {"item": "1004640001", "count": "1"}, {"item": "1005000021", "count": "1"}, {"item": "1006240001", "count": "1"}], "smallest": "10006340001", "count": "330", "cardinality": "310"}, "format": {"precisionStyle": "standard", "noCommas": "true", "align": "right"}, "flags": null}, {"id": 575834809, "name": "Census Tract", "fieldName": "census_tract", "position": 28, "description": "Census Tract (CT) - Permanent statistical subdivisions to provide a stable set of geographic units for the presentation of statistical data", "width": 357, "dataTypeName": "text", "renderTypeName": "text", "tableColumnId": 140081338, "cachedContents": {"non_null": "316", "largest": "SI-8", "null": "14", "top": [{"item": "qu-1", "count": "10"}, {"item": "bk-53", "count": "8"}, {"item": "qu-1579.02", "count": "5"}, {"item": "qu-309.04", "count": "5"}, {"item": "qu-33", "count": "5"}, {"item": "mn-79", "count": "4"}, {"item": "qu-907", "count": "4"}, {"item": "qu-294", "count": "4"}, {"item": "323", "count": "3"}, {"item": "bx-210.02", "count": "3"}, {"item": "bk-1098", "count": "3"}, {"item": "bx-212", "count": "3"}, {"item": "BK-447", "count": "3"}, {"item": "2009300", "count": "3"}, {"item": "5002100", "count": "3"}, {"item": "QU-444", "count": "3"}, {"item": "4020800", "count": "2"}, {"item": "1002900", "count": "2"}, {"item": "BX-379", "count": "2"}, {"item": "BX-235.02", "count": "2"}], "smallest": "1000600", "count": "330", "cardinality": "240"}, "format": {"precisionStyle": "standard", "noCommas": "true", "align": "right"}, "flags": null}, {"id": 575834810, "name": "Location 1", "fieldName": "location_1", "position": 29, "description": "The exact latitude and longitude of each Kiosk. \n", "width": 220, "dataTypeName": "location", "renderTypeName": "location", "tableColumnId": 35863889, "format": {"align": "left"}, "flags": null}], "commentUrl": null, "createdAt": "2016-04-25T16:05:24.000+00:00", "csvResourceUrl": "https://data.cityofnewyork.us/resource/xp25-gxux.csv", "customMetadataFieldsets": [{"name": "Dataset Information", "fields": [{"type": "fixed", "required": false, "private": false, "options": ["311", "Administration for Children's Services (ACS)", "Alliance for Downtown New York", "Banking Commission", "Board of Correction (BOC)", "Board of Elections (BOENY)", "Board of Standards and Appeals (BSA)", "Bronx Borough President (BPBX)", "Brooklyn Borough President (BPBK)", "Brooklyn Public Library (BPL)", "Business Integrity Commission (BIC)", "Campaign Finance Board (CFB)", "City Clerk & Clerk of the Council (OCC)", "City Council (NYCC)", "City Employees' Retirement System (NYCERS)", "City University of New York (CUNY)", "Civil Service Commission", "Civilian Complaint Review Board (CCRB)", "Commission on Human Rights (CCHR)", "Commission on Women's Issues (CWI)", "Commission to Combat Police Corruption (CCPC)", "Community Boards", "Conflicts of Interest Board (COIB)", "Department for the Aging (NYC Aging)", "Department of Buildings (DOB)", "Department of City Planning (DCP)", "Department of Citywide Administrative Services (DCAS)", "Department of Consumer and Worker Protection (DCWP)", "Department of Correction (DOC)", "Department of Cultural Affairs (DCLA)", "Department of Design and Construction (DDC)", "Department of Education (DOE)", "Department of Environmental Protection (DEP)", "Department of Finance (DOF)", "Department of Health and Mental Hygiene (DOHMH)", "Department of Homeless Services (DHS)", "Department of Housing Preservation and Development (HPD)", "Department of Information Technology & Telecommunications (DoITT)", "Department of Investigation (DOI)", "Department of Parks and Recreation (DPR)", "Department of Probation (DOP)", "Department of Records and Information Services (DORIS)", "Department of Sanitation (DSNY)", "Department of Small Business Services (SBS)", "Department of Transportation (DOT)", "Department of Veterans\u2019 Services (DVS)", "Department of Youth and Community Development (DYCD)", "Economic Development Corporation (NYCEDC)", "Equal Employment Practices Commission (EEPC)", "Financial Information Services Agency (FISA)", "Fire Department Pension Fund & Related Funds", "Fire Department of New York City (FDNY)", "HHS Accelerator", "Human Resources Administration (HRA)", "Landmarks Preservation Commission (LPC)", "Latin Media & Entertainment Commission (LMEC)", "Law Department (LAW)", "Loft Board (LOFT)", "Manhattan Borough President (MBPO)", "Mayor's Community Affairs Unit (CAU)", "Mayor's Office for Economic Opportunity", "Mayor's Office of Adult Education (ADULTED)", "Mayor's Office of Climate Resiliency", "Mayor's Office of Climate and Environmental Justice (MOCEJ)", "Mayor's Office of Climate and Sustainability", "Mayor's Office of Contract Services (MOCS)", "Mayor's Office of Criminal Justice (MOCJ)", "Mayor's Office of Ethnic and Community Media (MOECM)", "Mayor's Office of Food Policy (MOFP)", "Mayor's Office of Housing Recovery Operations (HRO)", "Mayor's Office of Management & Budget (OMB)", "Mayor's Office of Media And Entertainment (MOME)", "Mayor's Office of Operations (OPS)", "Mayor's Office of Recovery and Resiliency", "Mayor's Office of Special Enforcement (OSE)", "Mayor's Office of the Chief Technology Officer (MOCTO)", "Mayor\u2019s Office of Community Mental Health (OCMH)", "Mayor\u2019s Office of Environmental Coordination (MOEC)", "Mayor\u2019s Office of Environmental Remediation (MOER)", "Mayor\u2019s Office of Immigrant Affairs (MOIA)", "Mayor\u2019s Office to End Domestic and Gender-Based Violence", "Metropolitan Transportation Authority (MTA)", "NYC & Company (NYCGO)", "NYC Civic Engagement Commission", "NYC Emergency Management (NYCEM)", "NYC Health + Hospitals", "NYC Independent Budget Office (IBO)", "NYC Media (MEDIA)", "NYC Service (NYCSERVICE)", "New York City Housing Authority (NYCHA)", "New York City Tax Commission (TAXCOMM)", "New York Public Library (NYPL)", "New York Public Library (NYPL)", "Office of Administrative Tax Appeals (OATA)", "Office of Administrative Trials and Hearings (OATH)", "Office of Chief Medical Examiner (OCME)", "Office of Citywide Event Coordination and Management (CECM)", "Office of Collective Bargaining (OCB)", "Office of Film, Theatre, and Broadcasting (FILM)", "Office of Labor Relations (OLR)", "Office of Payroll Administration (OPA)", "Office of Technology and Innovation (OTI)", "Office of the Actuary (ACTUARY)", "Office of the Comptroller (COMPTROLLER)", "Office of the Mayor (OTM)", "Other", "Police Department (NYPD)", "Police Pension Fund (NYCPPF)", "Port Authority of New York & New Jersey (PANYNJ)", "Procurement Policy Board (PPB)", "Public Design Commission (formerly Art Commission (ARTCOM) and Design Commission)", "Queens Borough President (QBP)", "Queens Library (QBPL)", "Rent Guidelines Board (RGB)", "School Construction Authority (SCA)", "Staten Island Borough President (BPSI)", "Tax Appeals Tribunal (TAT)", "Taxi and Limousine Commission (TLC)", "Teachers Retirement System (TRSNYC)"], "name": "Agency"}], "existing_fields": {"Agency": "Office of Technology and Innovation (OTI)"}}, {"name": "Update", "fields": [{"type": "fixed", "required": true, "private": false, "options": ["Annually", "As needed", "Daily", "Every 10 years", "Every 2 months", "Every 2 weeks", "Every 2 years", "Every 3 years", "Every 4 months", "Every 4 years", "Every 5 years", "Every 6 months", "Every weekday", "Historical data", "Monthly", "Other", "Quarterly", "To be determined", "Weekly"], "name": "Update Frequency"}, {"type": "fixed", "required": true, "private": false, "options": ["Yes", "No"], "name": "Automation"}, {"required": false, "private": false, "name": "Date Made Public"}, {"required": false, "private": false, "name": "Update Frequency Details"}, {"required": false, "private": false, "name": "Data Change Frequency"}], "existing_fields": {"Automation": "No", "Date Made Public": "4/28/2016", "Update Frequency": "As needed"}}], "dsmapiScheduledUpdates": {}, "dsmapiAutomationGuidance": {}, "description": "LinkNYC is the City\u2019s program to provide free high-speed Wi-Fi, nationwide calling, a dedicated 911 button, charging ports for mobile devices, and access to social services. The City has recently begun to roll out a new and improved design of the original LinkNYC kiosk: Link5G. This new design will provide all of the amenities of LinkNYC kiosks, with the added benefit of 4G and 5G connectivity to enhance mobile telecommunications networks. This dataset lists proposed new locations for LinkNYC kiosks that are currently open for public comment.", "disableContactDatasetOwner": true, "editMetadataUrl": null, "editUrl": "/Social-Services/LinkNYC-New-Site-Permit-Applications/xp25-gxux/edit", "emailShareUrl": "mailto:?subject=LinkNYC New Site Permit Applications&body=Here is a dataset from NYC Open Data that I would like to share with you: https%3A%2F%2Fdata.cityofnewyork.us%2FSocial-Services%2FLinkNYC-New-Site-Permit-Applications%2Fxp25-gxux", "exploreUrl": "/Social-Services/LinkNYC-New-Site-Permit-Applications/xp25-gxux/explore", "exportFormats": ["csv", "csv_for_excel", "csv_for_excel_europe", "json", "rdf", "rss", "tsv_for_excel", "xml"], "facebookShareUrl": "http://www.facebook.com/sharer/sharer.php?u=https%3A%2F%2Fdata.cityofnewyork.us%2FSocial-Services%2FLinkNYC-New-Site-Permit-Applications%2Fxp25-gxux", "geoJsonResourceUrl": "https://data.cityofnewyork.us/resource/xp25-gxux.geojson", "gridUrl": "/Social-Services/LinkNYC-New-Site-Permit-Applications/xp25-gxux/data", "hasViewerGrant": true, "id": "xp25-gxux", "isBlobby": false, "isHref": false, "isPrivate": false, "isTabular": true, "isUnpublished": false, "lastUpdatedAt": "2023-06-21T18:55:56.000+00:00", "licenseLink": null, "licenseLogo": null, "licenseName": null, "metadata": {"rdfSubject": "0", "attachments": [{"filename": "LinkNYC New Site Permit Applications_Data Dictionary.xlsx", "assetId": "af747b23-07c3-499c-adea-2b1a589f536e", "name": "LinkNYC New Site Permit Applications_Data Dictionary.xlsx"}], "custom_fields": {"Update": {"Automation": "No", "Date Made Public": "4/28/2016", "Update Frequency": "As needed"}, "Dataset Information": {"Agency": "Office of Technology and Innovation (OTI)"}}, "rowLabel": "new site permit application for a Link NYC kiosk", "availableDisplayTypes": ["table", "fatrow", "page"], "renderTypeConfig": {"visible": {"table": true}}, "flags": []}, "name": "LinkNYC New Site Permit Applications", "namedResourceUrl": null, "openRevisions": [], "odataUrl": "https://data.cityofnewyork.us/OData.svc/xp25-gxux", "odataUrlV4": "https://data.cityofnewyork.us/api/odata/v4/xp25-gxux", "ownerName": "NYC OpenData", "permissions": null, "plotlyUrl": "https://data.cityofnewyork.us/api/views/xp25-gxux/rows.json", "provenance": "official", "resourceUrl": "https://data.cityofnewyork.us/resource/xp25-gxux.json", "rowLabel": "new site permit application for a Link NYC kiosk", "rowLabelMultiple": "new site permit application for a Link NYC kiosks", "tags": ["map", "gis", "geographic", "geospatial", "link", "citybridge", "wi-fi kiosk", "wi fi kiosks", "wifi"], "twitterShareUrl": "http://twitter.com/share?text=LinkNYC%20New%20Site%20Permit%20Applications%20%7C%20NYC%20Open%20Data&url=https%3A%2F%2Fdata.cityofnewyork.us%2FSocial-Services%2FLinkNYC-New-Site-Permit-Applications%2Fxp25-gxux", "viewCount": 5514, "coreView": {"id": "xp25-gxux", "name": "LinkNYC New Site Permit Applications", "assetType": "dataset", "attribution": "Office of Technology and Innovation (OTI)", "averageRating": 0.0, "category": "Social Services", "createdAt": 1461600324, "description": "LinkNYC is the City\u2019s program to provide free high-speed Wi-Fi, nationwide calling, a dedicated 911 button, charging ports for mobile devices, and access to social services. The City has recently begun to roll out a new and improved design of the original LinkNYC kiosk: Link5G. This new design will provide all of the amenities of LinkNYC kiosks, with the added benefit of 4G and 5G connectivity to enhance mobile telecommunications networks. This dataset lists proposed new locations for LinkNYC kiosks that are currently open for public comment.", "displayType": "table", "domainCName": "data.cityofnewyork.us", "downloadCount": 1835, "hideFromCatalog": false, "hideFromDataJson": false, "newBackend": true, "numberOfComments": 0, "oid": 39594517, "provenance": "official", "publicationAppendEnabled": false, "publicationDate": 1684245681, "publicationGroup": 10272415, "publicationStage": "published", "rowsUpdatedAt": 1687373756, "rowsUpdatedBy": "6ara-h3jt", "tableId": 19155812, "totalTimesRated": 0, "viewCount": 5514, "viewLastModified": 1687373754, "viewType": "tabular", "approvals": [{"reviewedAt": 1555010597, "reviewedAutomatically": true, "state": "approved", "submissionId": 5515040, "submissionObject": "public_audience_request", "submissionOutcome": "change_audience", "submittedAt": 1555010597, "targetAudience": "public", "workflowId": 2285, "submissionDetails": {"permissionType": "READ"}, "submissionOutcomeApplication": {"failureCount": 0, "status": "success"}, "submitter": {"id": "5fuc-pqz2", "displayName": "NYC OpenData"}}], "clientContext": {"clientContextVariables": [], "inheritedVariables": {}}, "columns": [{"id": 575834780, "name": "Site ID", "fieldName": "site_id", "position": 1, "description": "The unique ID for each LinkNYC kiosk site in the format: Borough-Community Board-Payphone ID (e.g., mn-03-123265) ", "width": 100, "dataTypeName": "text", "renderTypeName": "text", "tableColumnId": 68608596, "cachedContents": {"non_null": "330", "largest": "SI-01-GF55246", "null": "0", "top": [{"item": "BX-10-GF22747", "count": "1"}, {"item": "MN-12-120807", "count": "1"}, {"item": "MN-08-GF0910", "count": "1"}, {"item": "QU-12-GF44832", "count": "1"}, {"item": "QU-13-GF44801", "count": "1"}, {"item": "BK-16-150013", "count": "1"}, {"item": "MN-11-GF0922", "count": "1"}, {"item": "QU-10-GF44812", "count": "1"}, {"item": "QU-12-124672", "count": "1"}, {"item": "BK-16-132774", "count": "1"}, {"item": "MN-09-120409", "count": "1"}, {"item": "MN-08-GF0909", "count": "1"}, {"item": "SI-01-159857", "count": "1"}, {"item": "QU-01-GF44791", "count": "1"}, {"item": "BK-01-GF34906", "count": "1"}, {"item": "BK-11-GF34845", "count": "1"}, {"item": "BX-02-GF22617", "count": "1"}, {"item": "QU-13-GF44807", "count": "1"}, {"item": "BK-03-144136", "count": "1"}, {"item": "BK-16-158252", "count": "1"}], "smallest": "BK-01-125285", "count": "330", "cardinality": "330"}, "format": {"align": "left"}, "flags": null}, {"id": 575834781, "name": "Planned Kiosk Type", "fieldName": "planned_kiosk_type", "position": 2, "description": "Indicates style of kiosk (LINK1.0, LINK5G, and LINK5G_NoAd) or public pay phone.", "dataTypeName": "text", "renderTypeName": "text", "tableColumnId": 146728824, "cachedContents": {"non_null": "330", "largest": "LINK5G_NonAd", "null": "0", "top": [{"item": "LINK5G_Ad", "count": "205"}, {"item": "LINK5G_NonAd", "count": "90"}, {"item": "LINK1.0", "count": "35"}], "smallest": "LINK1.0", "count": "330", "cardinality": "3"}, "format": {}, "flags": null}, {"id": 575834818, "name": "Installation Status ", "fieldName": "installation_status_", "position": 3, "description": "Indicates the current status, including planning for utility connections, DOT permitting, and construction.", "dataTypeName": "text", "renderTypeName": "text", "tableColumnId": 146972014, "cachedContents": {"non_null": "330", "largest": "Ready for PreCx", "null": "0", "top": [{"item": "PreCx", "count": "124"}, {"item": "Live", "count": "73"}, {"item": "Planning", "count": "58"}, {"item": "Installed", "count": "51"}, {"item": "Ready for Installation", "count": "11"}, {"item": "Ready for Activation", "count": "7"}, {"item": "Ready for PreCx", "count": "4"}, {"item": "Ready for Cx", "count": "2"}], "smallest": "Installed", "count": "330", "cardinality": "8"}, "format": {}, "flags": null}, {"id": 575834782, "name": "PPT ID", "fieldName": "ppt_id", "position": 4, "description": "An 6-digit ID generated by the database - a unique number for each LINK and Pay Public Telephone (PPT)", "dataTypeName": "text", "renderTypeName": "text", "tableColumnId": 139558285, "cachedContents": {"non_null": "134", "largest": "GF33287", "null": "196", "top": [{"item": "100042", "count": "1"}, {"item": "100074", "count": "1"}, {"item": "103162", "count": "1"}, {"item": "106058", "count": "1"}, {"item": "107137", "count": "1"}, {"item": "107629", "count": "1"}, {"item": "107770", "count": "1"}, {"item": "108654", "count": "1"}, {"item": "108732", "count": "1"}, {"item": "108912", "count": "1"}, {"item": "109192", "count": "1"}, {"item": "109283", "count": "1"}, {"item": "114989", "count": "1"}, {"item": "115284", "count": "1"}, {"item": "118455", "count": "1"}, {"item": "118473", "count": "1"}, {"item": "118523", "count": "1"}, {"item": "118847", "count": "1"}, {"item": "119607", "count": "1"}, {"item": "119612", "count": "1"}], "smallest": "100042", "count": "330", "cardinality": "134"}, "format": {}, "flags": null}, {"id": 575834783, "name": "Legacy ID", "fieldName": "legacy_id", "position": 5, "description": "The ID number for the LinkNYC kiosk", "dataTypeName": "text", "renderTypeName": "text", "tableColumnId": 146316267, "cachedContents": {"non_null": "130", "largest": "SC90851", "null": "200", "top": [{"item": "10058", "count": "1"}, {"item": "10100", "count": "1"}, {"item": "10375", "count": "1"}, {"item": "10511", "count": "1"}, {"item": "12103", "count": "1"}, {"item": "12120", "count": "1"}, {"item": "12319", "count": "1"}, {"item": "12320", "count": "1"}, {"item": "12322", "count": "1"}, {"item": "1255", "count": "1"}, {"item": "13070", "count": "1"}, {"item": "1355", "count": "1"}, {"item": "14136", "count": "1"}, {"item": "14138", "count": "1"}, {"item": "14142", "count": "1"}, {"item": "14173", "count": "1"}, {"item": "1435", "count": "1"}, {"item": "15000", "count": "1"}, {"item": "15023", "count": "1"}, {"item": "15048", "count": "1"}], "smallest": "10058", "count": "330", "cardinality": "130"}, "format": {}, "flags": null}, {"id": 575834784, "name": "Borough", "fieldName": "borough", "position": 6, "description": "The New York City borough where the hotspots are located.\n", "width": 184, "dataTypeName": "text", "renderTypeName": "text", "tableColumnId": 35863871, "cachedContents": {"non_null": "330", "largest": "Staten Island", "null": "0", "top": [{"item": "Queens", "count": "135"}, {"item": "Brooklyn", "count": "81"}, {"item": "Manhattan", "count": "52"}, {"item": "Bronx", "count": "46"}, {"item": "Staten Island", "count": "16"}], "smallest": "Bronx", "count": "330", "cardinality": "5"}, "format": {"align": "left"}, "flags": null}, {"id": 575834785, "name": "Council District", "fieldName": "council_district", "position": 7, "description": "Council District is the lawmaking body of the City of New York.  There are 51 districts throughout NYC's five boroughs.", "width": 100, "dataTypeName": "number", "renderTypeName": "number", "tableColumnId": 54034269, "cachedContents": {"non_null": "330", "largest": "50", "null": "0", "top": [{"item": "27", "count": "38"}, {"item": "26", "count": "23"}, {"item": "28", "count": "17"}, {"item": "49", "count": "14"}, {"item": "1", "count": "14"}, {"item": "17", "count": "13"}, {"item": "10", "count": "13"}, {"item": "4", "count": "12"}, {"item": "34", "count": "12"}, {"item": "23", "count": "11"}, {"item": "33", "count": "11"}, {"item": "38", "count": "11"}, {"item": "42", "count": "11"}, {"item": "31", "count": "11"}, {"item": "24", "count": "10"}, {"item": "41", "count": "10"}, {"item": "15", "count": "9"}, {"item": "18", "count": "9"}, {"item": "37", "count": "8"}, {"item": "35", "count": "7"}], "smallest": "1", "count": "330", "cardinality": "41"}, "format": {"precisionStyle": "standard", "align": "left"}, "flags": null}, {"id": 575834786, "name": "Community Board", "fieldName": "cb", "position": 8, "description": "Community Board: An appointed advisory group from a variety of districts throughout NYC's five boroughs.  They deal with issues such as zoning, land usage, and any other matter related to the quality of life of their residents.\n", "width": 124, "dataTypeName": "number", "renderTypeName": "number", "tableColumnId": 35863873, "cachedContents": {"non_null": "330", "largest": "501", "null": "0", "top": [{"item": "412", "count": "66"}, {"item": "103", "count": "19"}, {"item": "402", "count": "17"}, {"item": "304", "count": "17"}, {"item": "501", "count": "16"}, {"item": "202", "count": "15"}, {"item": "316", "count": "15"}, {"item": "112", "count": "13"}, {"item": "205", "count": "12"}, {"item": "403", "count": "11"}, {"item": "413", "count": "11"}, {"item": "108", "count": "9"}, {"item": "306", "count": "8"}, {"item": "301", "count": "8"}, {"item": "207", "count": "8"}, {"item": "209", "count": "7"}, {"item": "414", "count": "7"}, {"item": "309", "count": "7"}, {"item": "407", "count": "7"}, {"item": "302", "count": "7"}], "smallest": "102", "count": "330", "cardinality": "39"}, "format": {"precisionStyle": "standard", "align": "right"}, "flags": null}, {"id": 575834788, "name": "Final Submission (A)", "fieldName": "final_submission_a_", "position": 9, "description": "Submission Date from vendor for review.", "dataTypeName": "calendar_date", "renderTypeName": "calendar_date", "tableColumnId": 146728823, "cachedContents": {"non_null": "326", "largest": "2023-04-06T00:00:00.000", "null": "4", "top": [{"item": "2022-08-09T00:00:00.000", "count": "103"}, {"item": "2021-10-08T00:00:00.000", "count": "52"}, {"item": "2021-11-30T00:00:00.000", "count": "28"}, {"item": "2022-09-23T00:00:00.000", "count": "28"}, {"item": "2022-03-08T00:00:00.000", "count": "21"}, {"item": "2022-11-17T00:00:00.000", "count": "19"}, {"item": "2022-01-28T00:00:00.000", "count": "16"}, {"item": "2021-08-31T00:00:00.000", "count": "12"}, {"item": "2022-04-01T00:00:00.000", "count": "12"}, {"item": "2022-05-13T00:00:00.000", "count": "10"}, {"item": "2022-10-28T00:00:00.000", "count": "7"}, {"item": "2021-12-21T00:00:00.000", "count": "5"}, {"item": "2022-11-03T00:00:00.000", "count": "2"}, {"item": "2021-04-06T00:00:00.000", "count": "2"}, {"item": "2021-08-06T00:00:00.000", "count": "2"}, {"item": "2021-05-14T00:00:00.000", "count": "2"}, {"item": "2022-02-23T00:00:00.000", "count": "1"}, {"item": "2022-08-17T00:00:00.000", "count": "1"}, {"item": "2023-02-10T00:00:00.000", "count": "1"}, {"item": "2022-09-16T00:00:00.000", "count": "1"}], "smallest": "2021-04-06T00:00:00.000", "count": "330", "cardinality": "21"}, "format": {}, "flags": null}, {"id": 575834789, "name": "GF Permit Application ID", "fieldName": "gf_permit_appl_id", "position": 10, "description": "The new site permit application number.\n", "width": 220, "dataTypeName": "number", "renderTypeName": "number", "tableColumnId": 35863882, "cachedContents": {"non_null": "225", "largest": "90459", "null": "105", "top": [{"item": "90196", "count": "2"}, {"item": "90198", "count": "2"}, {"item": "90199", "count": "2"}, {"item": "90452", "count": "1"}, {"item": "11765", "count": "1"}, {"item": "90110", "count": "1"}, {"item": "90245", "count": "1"}, {"item": "90434", "count": "1"}, {"item": "90200", "count": "1"}, {"item": "90433", "count": "1"}, {"item": "71381", "count": "1"}, {"item": "81286", "count": "1"}, {"item": "90170", "count": "1"}, {"item": "90459", "count": "1"}, {"item": "90225", "count": "1"}, {"item": "90307", "count": "1"}, {"item": "90354", "count": "1"}, {"item": "90157", "count": "1"}, {"item": "90176", "count": "1"}, {"item": "90202", "count": "1"}], "smallest": "11765", "count": "330", "cardinality": "222"}, "format": {"precisionStyle": "standard", "noCommas": "true", "align": "right"}, "flags": null}, {"id": 575834790, "name": "GF DoITT Submitted to CB (A)", "fieldName": "gf_doitt_submitted_to_cb_a", "position": 11, "description": "Information Submitted to Community Board on this date\n", "width": 100, "dataTypeName": "calendar_date", "renderTypeName": "calendar_date", "tableColumnId": 47417518, "cachedContents": {"non_null": "213", "largest": "2023-01-04T00:00:00.000", "null": "117", "top": [{"item": "2023-01-04T00:00:00.000", "count": "90"}, {"item": "2022-11-16T00:00:00.000", "count": "22"}, {"item": "2022-10-17T00:00:00.000", "count": "17"}, {"item": "2021-10-28T00:00:00.000", "count": "16"}, {"item": "2022-02-11T00:00:00.000", "count": "14"}, {"item": "2022-10-18T00:00:00.000", "count": "12"}, {"item": "2021-09-23T00:00:00.000", "count": "11"}, {"item": "2022-05-13T00:00:00.000", "count": "9"}, {"item": "2022-04-08T00:00:00.000", "count": "8"}, {"item": "2022-11-18T00:00:00.000", "count": "8"}, {"item": "2022-11-17T00:00:00.000", "count": "4"}, {"item": "2021-11-22T00:00:00.000", "count": "2"}], "smallest": "2021-09-23T00:00:00.000", "count": "330", "cardinality": "12"}, "format": {"view": "date", "align": "left"}, "flags": null}, {"id": 575834791, "name": "GF CB Comment Period Ends (A)", "fieldName": "gf_cb_comment_period_ends_a", "position": 12, "description": "Community Board Comment Period Ends on this date\n", "width": 100, "dataTypeName": "calendar_date", "renderTypeName": "calendar_date", "tableColumnId": 47417519, "cachedContents": {"non_null": "30", "largest": "2022-12-18T00:00:00.000", "null": "300", "top": [{"item": "2021-12-27T00:00:00.000", "count": "16"}, {"item": "2021-11-22T00:00:00.000", "count": "11"}, {"item": "2022-01-24T00:00:00.000", "count": "2"}, {"item": "2022-12-18T00:00:00.000", "count": "1"}], "smallest": "2021-11-22T00:00:00.000", "count": "330", "cardinality": "4"}, "format": {"view": "date", "align": "left"}, "flags": null}, {"id": 575834792, "name": "Street Address", "fieldName": "street_address", "position": 13, "description": "The name of the street that a site is located on.\n", "width": 232, "dataTypeName": "text", "renderTypeName": "text", "tableColumnId": 35863875, "cachedContents": {"non_null": "330", "largest": "CLASON POINT PARK", "null": "0", "top": [{"item": "75-20 ASTORIA BOULEVARD", "count": "2"}, {"item": "4228 MAIN STREET", "count": "1"}, {"item": "689 FT WASHINGTON AVENUE", "count": "1"}, {"item": "660 FLATBUSH AVENUE", "count": "1"}, {"item": "1354 MADISON AVENUE", "count": "1"}, {"item": "3177 WEBSTER AVENUE", "count": "1"}, {"item": "84 BEARD STREET", "count": "1"}, {"item": "18 BELMONT AVENUE", "count": "1"}, {"item": "184 CONOVER STREET", "count": "1"}, {"item": "1175 PARK AVENUE", "count": "1"}, {"item": "700 FAILE STREET", "count": "1"}, {"item": "40-39 CRESCENT STREET", "count": "1"}, {"item": "100 HORATIO STREET", "count": "1"}, {"item": "408 DE WITT AVENUE", "count": "1"}, {"item": "2861 WEBSTER AVENUE", "count": "1"}, {"item": "303 STANLEY AVENUE", "count": "1"}, {"item": "81-14 257TH STREET", "count": "1"}, {"item": "175 LYNHURST AVENUE", "count": "1"}, {"item": "1572 PITKIN AVENUE", "count": "1"}, {"item": "168-20 HILLSIDE AVENUE", "count": "1"}], "smallest": "100 HORATIO STREET", "count": "330", "cardinality": "329"}, "format": {"align": "left"}, "flags": null}, {"id": 575834793, "name": "Cross_Street 1", "fieldName": "cross_street_1", "position": 14, "description": "One of the closest streets to a potential LinkNYC site.\n", "width": 268, "dataTypeName": "text", "renderTypeName": "text", "tableColumnId": 35863876, "cachedContents": {"non_null": "330", "largest": "Zerega Ave", "null": "0", "top": [{"item": "BEDFORD AVENUE", "count": "4"}, {"item": "VICTORY BOULEVARD", "count": "4"}, {"item": "BROADWAY", "count": "4"}, {"item": "JUNIUS STREET", "count": "4"}, {"item": "41st Ave", "count": "4"}, {"item": "5th St", "count": "3"}, {"item": "HILLSIDE AVENUE", "count": "3"}, {"item": "Sutphin Boulevard", "count": "3"}, {"item": "WEST STREET", "count": "2"}, {"item": "EAST 93RD STREET", "count": "2"}, {"item": "Northern Boulevard", "count": "2"}, {"item": "262nd ST", "count": "2"}, {"item": "GRAND STREET", "count": "2"}, {"item": "BEARD STREET", "count": "2"}, {"item": "MYRTLE AVENUE", "count": "2"}, {"item": "Merrick Boulevard", "count": "2"}, {"item": "Louisiana Ave", "count": "2"}, {"item": "GATES AVENUE", "count": "2"}, {"item": "122ND STREET", "count": "2"}, {"item": "SOUTHERN BOULEVARD", "count": "2"}], "smallest": "107TH AVENUE", "count": "330", "cardinality": "285"}, "format": {"align": "left"}, "flags": null}, {"id": 575834794, "name": "Cross_Street 2", "fieldName": "cross_street_2", "position": 15, "description": "One of the closest streets to a potential LinkNYC site.\n", "width": 268, "dataTypeName": "text", "renderTypeName": "text", "tableColumnId": 35863877, "cachedContents": {"non_null": "330", "largest": "Zoller Road", "null": "0", "top": [{"item": "261st ST", "count": "3"}, {"item": "POWELL STREET", "count": "3"}, {"item": "Dead End", "count": "3"}, {"item": "DEAD END", "count": "3"}, {"item": "EAST 92ND STREET", "count": "2"}, {"item": "MONTGOMERY STREET", "count": "2"}, {"item": "CANAL STREET", "count": "2"}, {"item": "52nd Street", "count": "2"}, {"item": "ANTHONY AVENUE", "count": "2"}, {"item": "LORING PLACE SOUTH", "count": "2"}, {"item": "HARRISON AVENUE", "count": "2"}, {"item": "BARRY STREET", "count": "2"}, {"item": "264th ST", "count": "2"}, {"item": "MYRTLE AVENUE", "count": "2"}, {"item": "PURDY AVENUE", "count": "2"}, {"item": "Queens Plaza N", "count": "2"}, {"item": "VAN DYKE STREET", "count": "2"}, {"item": "W 167 STREET", "count": "2"}, {"item": "Dunkirk Drive", "count": "2"}, {"item": "STANTON STREET", "count": "2"}], "smallest": "109th Avenue", "count": "330", "cardinality": "301"}, "format": {"align": "left"}, "flags": null}, {"id": 575834795, "name": "IxN Corner", "fieldName": "ixn_code", "position": 16, "description": "The direction the Kiosk is facing.", "dataTypeName": "text", "renderTypeName": "text", "tableColumnId": 146728822, "cachedContents": {"non_null": "329", "largest": "West", "null": "1", "top": [{"item": "S", "count": "74"}, {"item": "E", "count": "70"}, {"item": "N", "count": "66"}, {"item": "W", "count": "62"}, {"item": "West", "count": "16"}, {"item": "North", "count": "14"}, {"item": "East", "count": "11"}, {"item": "South", "count": "8"}, {"item": "NW", "count": "4"}, {"item": "SE", "count": "2"}, {"item": "NE", "count": "1"}, {"item": "SW", "count": "1"}], "smallest": "E", "count": "330", "cardinality": "12"}, "format": {}, "flags": null}, {"id": 575834796, "name": "Postcode", "fieldName": "postcode", "position": 17, "description": "Five (5) digit postal code assigned by the United States Postal Service. ", "width": 100, "dataTypeName": "number", "renderTypeName": "number", "tableColumnId": 54034288, "cachedContents": {"non_null": "330", "largest": "11694", "null": "0", "top": [{"item": "11101", "count": "19"}, {"item": "11412", "count": "14"}, {"item": "11434", "count": "13"}, {"item": "10002", "count": "12"}, {"item": "11212", "count": "11"}, {"item": "11237", "count": "11"}, {"item": "11433", "count": "11"}, {"item": "11435", "count": "9"}, {"item": "11432", "count": "8"}, {"item": "11423", "count": "8"}, {"item": "11231", "count": "8"}, {"item": "11004", "count": "7"}, {"item": "10462", "count": "7"}, {"item": "10474", "count": "7"}, {"item": "11354", "count": "6"}, {"item": "11207", "count": "6"}, {"item": "10301", "count": "6"}, {"item": "10467", "count": "5"}, {"item": "10459", "count": "5"}, {"item": "10014", "count": "5"}], "smallest": "10002", "count": "330", "cardinality": "90"}, "format": {"precisionStyle": "standard", "noCommas": "true", "align": "right"}, "flags": null}, {"id": 575834797, "name": "Zoning", "fieldName": "zoningnumb", "position": 18, "description": "The type of zoning a kiosk is located in, displayed by its first letter followed by its zone.\n", "width": 220, "dataTypeName": "text", "renderTypeName": "text", "tableColumnId": 35863872, "cachedContents": {"non_null": "329", "largest": "R8 / C2-4", "null": "1", "top": [{"item": "C2-4", "count": "42"}, {"item": "C1-3", "count": "31"}, {"item": "M1-1", "count": "26"}, {"item": "C2-3", "count": "18"}, {"item": "C1-4", "count": "14"}, {"item": "C2-2", "count": "11"}, {"item": "M3-1", "count": "10"}, {"item": "M2-1", "count": "10"}, {"item": "C1-2", "count": "10"}, {"item": "M1-2", "count": "8"}, {"item": "C4-3", "count": "8"}, {"item": "C4-2", "count": "7"}, {"item": "C1-5", "count": "7"}, {"item": "R6", "count": "7"}, {"item": "R7-2", "count": "7"}, {"item": "M1-4", "count": "6"}, {"item": "R10", "count": "6"}, {"item": "C4-4", "count": "5"}, {"item": "C4-4A", "count": "5"}, {"item": "C8-2", "count": "5"}], "smallest": "C1-1", "count": "330", "cardinality": "67"}, "format": {"align": "left"}, "flags": null}, {"id": 575834798, "name": "Longitude", "fieldName": "longitude", "position": 19, "description": "Points that fall East or West of the Prime Meridian, expressed in degrees.\n", "width": 208, "dataTypeName": "number", "renderTypeName": "number", "tableColumnId": 35863870, "cachedContents": {"non_null": "330", "largest": "-73.7053516", "null": "0", "top": [{"item": "-74.141731", "count": "1"}, {"item": "-74.1406262", "count": "1"}, {"item": "-74.1373888", "count": "1"}, {"item": "-74.1346574", "count": "1"}, {"item": "-74.1301262", "count": "1"}, {"item": "-74.1277241", "count": "1"}, {"item": "-74.1192244", "count": "1"}, {"item": "-74.1033513", "count": "1"}, {"item": "-74.0804804", "count": "1"}, {"item": "-74.0779427", "count": "1"}, {"item": "-74.0776909", "count": "1"}, {"item": "-74.0771009", "count": "1"}, {"item": "-74.075901", "count": "1"}, {"item": "-74.0753967", "count": "1"}, {"item": "-74.0740457", "count": "1"}, {"item": "-74.0708488", "count": "1"}, {"item": "-74.0379322", "count": "1"}, {"item": "-74.025701", "count": "1"}, {"item": "-74.0170529", "count": "1"}, {"item": "-74.0168289", "count": "1"}], "smallest": "-74.141731", "count": "330", "cardinality": "330"}, "format": {"precisionStyle": "standard", "precision": "5", "align": "right"}, "flags": null}, {"id": 575834799, "name": "Latitude", "fieldName": "latitude", "position": 20, "description": "Points that fall North or South of the Equator, expressed in degrees.\n", "width": 196, "dataTypeName": "number", "renderTypeName": "number", "tableColumnId": 35863869, "cachedContents": {"non_null": "330", "largest": "40.8820398", "null": "0", "top": [{"item": "40.7489749", "count": "1"}, {"item": "40.6992378", "count": "1"}, {"item": "40.658116", "count": "1"}, {"item": "40.6717001", "count": "1"}, {"item": "40.762123", "count": "1"}, {"item": "40.8820398", "count": "1"}, {"item": "40.7484385", "count": "1"}, {"item": "40.8669715", "count": "1"}, {"item": "40.8387572", "count": "1"}, {"item": "40.771118", "count": "1"}, {"item": "40.745149", "count": "1"}, {"item": "40.7521201", "count": "1"}, {"item": "40.6797471", "count": "1"}, {"item": "40.7445751", "count": "1"}, {"item": "40.6781059", "count": "1"}, {"item": "40.6640729", "count": "1"}, {"item": "40.7538272", "count": "1"}, {"item": "40.634333", "count": "1"}, {"item": "40.736811", "count": "1"}, {"item": "40.7638316", "count": "1"}], "smallest": "40.5700406", "count": "330", "cardinality": "330"}, "format": {"precisionStyle": "standard", "precision": "5", "align": "right"}, "flags": null}, {"id": 575834800, "name": "Site in Business Improvement District (BID)?", "fieldName": "greenfield_in_bid_location", "position": 21, "description": "Is the LinkNYC Kiosk located in a Business Improvement District (BID)?\n", "width": 100, "dataTypeName": "text", "renderTypeName": "text", "tableColumnId": 45571080, "cachedContents": {"non_null": "322", "largest": "Yes", "null": "8", "top": [{"item": "No", "count": "296"}, {"item": "Yes", "count": "26"}], "smallest": "No", "count": "330", "cardinality": "2"}, "format": {"align": "left"}, "flags": null}, {"id": 575834801, "name": "BID", "fieldName": "bid", "position": 22, "description": "Is the LinkNYC Kiosk located in a Business Improvement District (BID)?\n", "width": 208, "dataTypeName": "text", "renderTypeName": "text", "tableColumnId": 35863880, "cachedContents": {"non_null": "29", "largest": "Village Alliance BID", "null": "301", "top": [{"item": "Chinatown", "count": "5"}, {"item": "Greater JFK", "count": "3"}, {"item": "Long Island City", "count": "2"}, {"item": "Jerome-Gun Hill", "count": "2"}, {"item": "Court-Livingston-Schermerhorn", "count": "2"}, {"item": "Lower East Side BID", "count": "2"}, {"item": "Myrtle Avenue Brooklyn Partnership?", "count": "2"}, {"item": "Pitkin Avenue", "count": "1"}, {"item": "Pitkin Avenue BID", "count": "1"}, {"item": "Southern Boulevard", "count": "1"}, {"item": "Sutphin Boulevard", "count": "1"}, {"item": "Village Alliance BID", "count": "1"}, {"item": "Church Avenue BID", "count": "1"}, {"item": "East Brooklyn BID", "count": "1"}, {"item": "Flatbush-Nostrand Junction?BID", "count": "1"}, {"item": "Madison Avenue", "count": "1"}, {"item": "Meatpacking", "count": "1"}, {"item": "Montague Street", "count": "1"}], "smallest": "Chinatown", "count": "330", "cardinality": "18"}, "format": {"align": "left"}, "flags": null}, {"id": 575834802, "name": "Link In Historic District", "fieldName": "historic_district", "position": 23, "description": "Is the LinkNYC Kiosk located in a historic district?\n", "width": 220, "dataTypeName": "text", "renderTypeName": "text", "tableColumnId": 35863878, "cachedContents": {"non_null": "330", "largest": "1", "null": "0", "top": [{"item": "0", "count": "326"}, {"item": "1", "count": "4"}], "smallest": "0", "count": "330", "cardinality": "2"}, "format": {"align": "left"}, "flags": null}, {"id": 575834803, "name": "Historic District Name", "fieldName": "historic_district_name", "position": 24, "description": "Name of historic district determined by the Landmarks Preservation Commission (LPC).", "dataTypeName": "text", "renderTypeName": "text", "tableColumnId": 146728821, "cachedContents": {"non_null": "9", "largest": "Upper East Side Historic District", "null": "321", "top": [{"item": "Expanded Carnegie Hill Historic District", "count": "2"}, {"item": "Park Avenue Historic District", "count": "2"}, {"item": "Upper East Side Historic District", "count": "2"}, {"item": "Gansevoort Market Historic District", "count": "1"}, {"item": "Greenwich Village Historic District", "count": "1"}, {"item": "SoHo-Cast Iron Historic District", "count": "1"}], "smallest": "Expanded Carnegie Hill Historic District", "count": "330", "cardinality": "6"}, "format": {}, "flags": null}, {"id": 575834804, "name": "Neighborhood Tabulation Area (NTA)", "fieldName": "neighborhood_tabulation_area_nta", "position": 25, "description": "Neighborhood identifiers to differentiate NYC's five boroughs\n", "width": 252, "dataTypeName": "text", "renderTypeName": "text", "tableColumnId": 54034554, "cachedContents": {"non_null": "323", "largest": "West Village", "null": "7", "top": [{"item": "Jamaica", "count": "22"}, {"item": "Hunters Point-Sunnyside-West Maspeth", "count": "17"}, {"item": "St. Albans", "count": "14"}, {"item": "Brownsville", "count": "13"}, {"item": "Hunts Point", "count": "11"}, {"item": "Jackson Heights", "count": "11"}, {"item": "Bushwick North", "count": "10"}, {"item": "Chinatown", "count": "9"}, {"item": "Upper East Side-Carnegie Hill", "count": "8"}, {"item": "Glen Oaks-Floral Park-New Hyde Park", "count": "8"}, {"item": "Carroll Gardens-Columbia Street-Red Hook", "count": "8"}, {"item": "Bushwick South", "count": "7"}, {"item": "Springfield Gardens North", "count": "7"}, {"item": "Hollis", "count": "6"}, {"item": "South Jamaica", "count": "6"}, {"item": "Queensbridge-Ravenswood-Long Island City", "count": "6"}, {"item": "Parkchester", "count": "6"}, {"item": "Washington Heights North", "count": "5"}, {"item": "Stapleton-Rosebank", "count": "5"}, {"item": "North Side-South Side", "count": "5"}], "smallest": "Baisley Park", "count": "330", "cardinality": "79"}, "format": {"align": "left"}, "flags": null}, {"id": 575834805, "name": "Building Identification Number (BIN)", "fieldName": "bin", "position": 26, "description": "Every real estate property has an assigned 7-digit number issued by the Department of City Planning.\n", "width": 100, "dataTypeName": "text", "renderTypeName": "text", "tableColumnId": 144101687, "cachedContents": {"non_null": "268", "largest": "5106796", "null": "62", "top": [{"item": "4541713", "count": "2"}, {"item": "2096680", "count": "2"}, {"item": "1000000", "count": "2"}, {"item": "1003219", "count": "1"}, {"item": "1003542", "count": "1"}, {"item": "1003627", "count": "1"}, {"item": "1003761", "count": "1"}, {"item": "1003957", "count": "1"}, {"item": "1004034", "count": "1"}, {"item": "1005433", "count": "1"}, {"item": "1005761", "count": "1"}, {"item": "1006068", "count": "1"}, {"item": "1007645", "count": "1"}, {"item": "1011368", "count": "1"}, {"item": "1012047", "count": "1"}, {"item": "1012154", "count": "1"}, {"item": "1034522", "count": "1"}, {"item": "1040861", "count": "1"}, {"item": "1040900", "count": "1"}, {"item": "1046915", "count": "1"}], "smallest": "1000000", "count": "330", "cardinality": "265"}, "format": {"precisionStyle": "standard", "noCommas": "true", "align": "right"}, "flags": null}, {"id": 575834807, "name": "Borough-Block-Lot( BBL)", "fieldName": "bbl", "position": 27, "description": "Every real estate property is identified by a set of 3 numbers for taxes, zoning, construction, and other purposes.\n", "width": 100, "dataTypeName": "text", "renderTypeName": "text", "tableColumnId": 144101688, "cachedContents": {"non_null": "319", "largest": "5028530001", "null": "11", "top": [{"item": "4010270050", "count": "3"}, {"item": "4000210020", "count": "2"}, {"item": "4122610001", "count": "2"}, {"item": "4000210040", "count": "2"}, {"item": "4087170001", "count": "2"}, {"item": "2039377501", "count": "2"}, {"item": "4043500050", "count": "2"}, {"item": "2039430001", "count": "2"}, {"item": "1003020001", "count": "1"}, {"item": "1003100020", "count": "1"}, {"item": "1003467501", "count": "1"}, {"item": "1003507502", "count": "1"}, {"item": "1003540012", "count": "1"}, {"item": "1003990008", "count": "1"}, {"item": "1004130008", "count": "1"}, {"item": "1004390028", "count": "1"}, {"item": "1004420007", "count": "1"}, {"item": "1004640001", "count": "1"}, {"item": "1005000021", "count": "1"}, {"item": "1006240001", "count": "1"}], "smallest": "10006340001", "count": "330", "cardinality": "310"}, "format": {"precisionStyle": "standard", "noCommas": "true", "align": "right"}, "flags": null}, {"id": 575834809, "name": "Census Tract", "fieldName": "census_tract", "position": 28, "description": "Census Tract (CT) - Permanent statistical subdivisions to provide a stable set of geographic units for the presentation of statistical data", "width": 357, "dataTypeName": "text", "renderTypeName": "text", "tableColumnId": 140081338, "cachedContents": {"non_null": "316", "largest": "SI-8", "null": "14", "top": [{"item": "qu-1", "count": "10"}, {"item": "bk-53", "count": "8"}, {"item": "qu-1579.02", "count": "5"}, {"item": "qu-309.04", "count": "5"}, {"item": "qu-33", "count": "5"}, {"item": "mn-79", "count": "4"}, {"item": "qu-907", "count": "4"}, {"item": "qu-294", "count": "4"}, {"item": "323", "count": "3"}, {"item": "bx-210.02", "count": "3"}, {"item": "bk-1098", "count": "3"}, {"item": "bx-212", "count": "3"}, {"item": "BK-447", "count": "3"}, {"item": "2009300", "count": "3"}, {"item": "5002100", "count": "3"}, {"item": "QU-444", "count": "3"}, {"item": "4020800", "count": "2"}, {"item": "1002900", "count": "2"}, {"item": "BX-379", "count": "2"}, {"item": "BX-235.02", "count": "2"}], "smallest": "1000600", "count": "330", "cardinality": "240"}, "format": {"precisionStyle": "standard", "noCommas": "true", "align": "right"}, "flags": null}, {"id": 575834810, "name": "Location 1", "fieldName": "location_1", "position": 29, "description": "The exact latitude and longitude of each Kiosk. \n", "width": 220, "dataTypeName": "location", "renderTypeName": "location", "tableColumnId": 35863889, "format": {"align": "left"}, "flags": null}], "grants": [{"inherited": false, "type": "viewer", "flags": ["public"]}], "metadata": {"rdfSubject": "0", "attachments": [{"filename": "LinkNYC New Site Permit Applications_Data Dictionary.xlsx", "assetId": "af747b23-07c3-499c-adea-2b1a589f536e", "name": "LinkNYC New Site Permit Applications_Data Dictionary.xlsx"}], "custom_fields": {"Update": {"Automation": "No", "Date Made Public": "4/28/2016", "Update Frequency": "As needed"}, "Dataset Information": {"Agency": "Office of Technology and Innovation (OTI)"}}, "rowLabel": "new site permit application for a Link NYC kiosk", "availableDisplayTypes": ["table", "fatrow", "page"], "renderTypeConfig": {"visible": {"table": true}}}, "owner": {"id": "5fuc-pqz2", "displayName": "NYC OpenData", "profileImageUrlLarge": "/api/users/5fuc-pqz2/profile_images/LARGE", "profileImageUrlMedium": "/api/users/5fuc-pqz2/profile_images/THUMB", "profileImageUrlSmall": "/api/users/5fuc-pqz2/profile_images/TINY", "screenName": "NYC OpenData", "type": "interactive", "flags": ["acceptedEula", "mayBeStoriesCoOwner"]}, "query": {}, "rights": ["read"], "tableAuthor": {"id": "5fuc-pqz2", "displayName": "NYC OpenData", "profileImageUrlLarge": "/api/users/5fuc-pqz2/profile_images/LARGE", "profileImageUrlMedium": "/api/users/5fuc-pqz2/profile_images/THUMB", "profileImageUrlSmall": "/api/users/5fuc-pqz2/profile_images/TINY", "screenName": "NYC OpenData", "type": "interactive", "flags": ["acceptedEula", "mayBeStoriesCoOwner"]}, "tags": ["map", "gis", "geographic", "geospatial", "link", "citybridge", "wi-fi kiosk", "wi fi kiosks", "wifi"], "flags": ["default", "ownerMayBeContacted", "restorable", "restorePossibleForType"], "computedColumns": [{"id": 575834813, "name": "Zip Codes", "fieldName": ":@computed_region_efsh_h5xi", "position": 37, "dataTypeName": "number", "renderTypeName": "number", "tableColumnId": 79124841, "computationStrategy": {"source_columns": ["location_1"], "type": "georegion_match_on_point", "parameters": {"region": "_efsh-h5xi", "primary_key": "_feature_id"}}, "format": {}, "flags": null}, {"id": 575834814, "name": "Community Districts", "fieldName": ":@computed_region_f5dn_yrer", "position": 38, "dataTypeName": "number", "renderTypeName": "number", "tableColumnId": 79124842, "computationStrategy": {"source_columns": ["location_1"], "type": "georegion_match_on_point", "parameters": {"region": "_f5dn-yrer", "primary_key": "_feature_id"}}, "format": {}, "flags": null}, {"id": 575834815, "name": "Borough Boundaries", "fieldName": ":@computed_region_yeji_bk3q", "position": 39, "dataTypeName": "number", "renderTypeName": "number", "tableColumnId": 79124843, "computationStrategy": {"source_columns": ["location_1"], "type": "georegion_match_on_point", "parameters": {"region": "_yeji-bk3q", "primary_key": "_feature_id"}}, "format": {}, "flags": null}, {"id": 575834816, "name": "City Council Districts", "fieldName": ":@computed_region_92fq_4b7q", "position": 40, "dataTypeName": "number", "renderTypeName": "number", "tableColumnId": 79124844, "computationStrategy": {"source_columns": ["location_1"], "type": "georegion_match_on_point", "parameters": {"region": "_92fq-4b7q", "primary_key": "_feature_id"}}, "format": {}, "flags": null}, {"id": 575834817, "name": "Police Precincts", "fieldName": ":@computed_region_sbqj_enih", "position": 41, "dataTypeName": "number", "renderTypeName": "number", "tableColumnId": 79124845, "computationStrategy": {"source_columns": ["location_1"], "type": "georegion_match_on_point", "parameters": {"region": "_sbqj-enih", "primary_key": "_feature_id"}}, "format": {}, "flags": null}]}}, "relatedViews": [{"name": "LinkNYC New-Site Permit Applications - Map", "id": "tdt4-7qzu", "description": "LinkNYC is replacing the City\u2019s outdated public telephones with a network of kiosks that provide free high-speed Wi-Fi, nationwide calling, a dedicated 911 button, charging ports for mobile devices, and access to selected websites. This dataset lists proposed new locations for LinkNYC kiosk that are currently open for public comment.  The dataset does not include payphones that are being replaced by Links.", "url": "https://data.cityofnewyork.us/Social-Services/LinkNYC-New-Site-Permit-Applications-Map/tdt4-7qzu", "displayType": "map", "isFederated": false, "createdAt": "2021-09-22T15:50:53.000Z", "updatedAt": "2023-06-21T18:55:56.000Z", "viewCount": 6287, "isPrivate": false, "imageUrl": null, "scope": "public", "sourceDomain": "data.cityofnewyork.us"}], "featuredContent": [], "websocketToken": null}